xpa/__init__.py
xpa/correction.py
xpa-0.1.0.dist-info/WHEEL
xpa-0.1.0.dist-info/METADATA
xpa-0.1.0.dist-info/RECORD
