Metadata-Version: 2.1
Name: xpa
Version: 0.1.0
Summary: X-ray diffraction lib for analysis
Author: Andre da Silva
Author-email: andrezio@live.com
Requires-Python: >=3.6.1,<4.0
Classifier: Programming Language :: Python :: 3
Classifier: Programming Language :: Python :: 3.7
Classifier: Programming Language :: Python :: 3.8
Classifier: Programming Language :: Python :: 3.9
Requires-Dist: numpy (>=1.19.4,<2.0.0)
Requires-Dist: pandas (>=1.1.4,<2.0.0)
Requires-Dist: scipy (>=1.5.4,<2.0.0)
